visionaire4/__init__.py
visionaire4/__main__.py
visionaire4/dataset.py
visionaire4/export.py
visionaire4/report.py
visionaire4/restore.py
visionaire4/utils.py
visionaire4/version.py
visionaire4/configs/__init__.py
visionaire4/configs/compose.py
visionaire4/configs/configs.py
visionaire4/configs/generator.py
visionaire4/configs/hybrid_dashboard.py
visionaire4/configs/resource_dashboard.py
visionaire4/configs/visionaire4_dashboard.py
visionaire4-0.1.0.dist-info/METADATA
visionaire4-0.1.0.dist-info/WHEEL
visionaire4-0.1.0.dist-info/entry_points.txt
visionaire4-0.1.0.dist-info/top_level.txt
visionaire4-0.1.0.dist-info/RECORD
