Metadata-Version: 2.1
Name: visionaire4
Version: 0.1.0
Summary: Visionaire4 maintenance tools suite
Home-page: https://pypi.org/project/visionaire4/
Author: Tri Wahyu Utomo
Author-email: tri@nodeflux.io
License: UNKNOWN
Platform: UNKNOWN
Requires-Python: >=3.6
Requires-Dist: docker (>=4.3.0)
Requires-Dist: imagesize
Requires-Dist: matplotlib
Requires-Dist: numpy
Requires-Dist: pyyaml
Requires-Dist: requests
Requires-Dist: tqdm (==4.64.1)
Provides-Extra: dev
Requires-Dist: flake8 ; extra == 'dev'
Requires-Dist: pytest ; extra == 'dev'
Requires-Dist: pytest-cov ; extra == 'dev'
Requires-Dist: twine ; extra == 'dev'
Requires-Dist: wheel ; extra == 'dev'
